odoo/addons/ir_actions_report_multi_company/README.rst
odoo/addons/ir_actions_report_multi_company/__init__.py
odoo/addons/ir_actions_report_multi_company/__manifest__.py
odoo/addons/ir_actions_report_multi_company/i18n/fr.po
odoo/addons/ir_actions_report_multi_company/i18n/ir_actions_report_multi_company.pot
odoo/addons/ir_actions_report_multi_company/i18n/it.po
odoo/addons/ir_actions_report_multi_company/models/__init__.py
odoo/addons/ir_actions_report_multi_company/models/ir_actions_actions.py
odoo/addons/ir_actions_report_multi_company/models/ir_actions_report.py
odoo/addons/ir_actions_report_multi_company/readme/CONTRIBUTORS.rst
odoo/addons/ir_actions_report_multi_company/readme/DESCRIPTION.rst
odoo/addons/ir_actions_report_multi_company/readme/USAGE.rst
odoo/addons/ir_actions_report_multi_company/security/multi_company.xml
odoo/addons/ir_actions_report_multi_company/static/description/icon.png
odoo/addons/ir_actions_report_multi_company/static/description/index.html
odoo/addons/ir_actions_report_multi_company/views/ir_actions_report_view.xml
odoo_addon_ir_actions_report_multi_company-16.0.1.0.0.4.dist-info/METADATA
odoo_addon_ir_actions_report_multi_company-16.0.1.0.0.4.dist-info/WHEEL
odoo_addon_ir_actions_report_multi_company-16.0.1.0.0.4.dist-info/top_level.txt
odoo_addon_ir_actions_report_multi_company-16.0.1.0.0.4.dist-info/RECORD
